pasteconnect/__init__.py
pasteconnect/pastebinclient.py
pasteconnect/reqsession.py
pasteconnect-0.6.2.dist-info/LICENSE
pasteconnect-0.6.2.dist-info/METADATA
pasteconnect-0.6.2.dist-info/WHEEL
pasteconnect-0.6.2.dist-info/top_level.txt
pasteconnect-0.6.2.dist-info/RECORD
