Metadata-Version: 2.1
Name: pasteconnect
Version: 0.6.2
Summary: Package to read and upload code/text to pastebin.com.
Home-page: https://github.com/heartlog/pasteconnect
Download-URL: https://github.com/heartlog/pasteconnect/releases
Author: Heartlog
Author-email: heartlog@skiff.com
Keywords: pastebin,pastebinapi,client,opensource
Classifier: Programming Language :: Python :: 3
Classifier: Programming Language :: Python :: 3.7
Classifier: Programming Language :: Python :: 3.8
Classifier: Programming Language :: Python :: 3.9
Classifier: Programming Language :: Python :: 3.10
Classifier: Programming Language :: Python :: 3.11
Classifier: Operating System :: OS Independent
Classifier: License :: OSI Approved :: MIT License
Classifier: Natural Language :: English
Requires-Python: >=3.7
License-File: LICENSE
Requires-Dist: requests
Requires-Dist: fake-useragent
Requires-Dist: python-dotenv
